LICENSE
MANIFEST.in
README.rst
setup.py
swot_simulator/__init__.py
swot_simulator/dispatch.py
swot_simulator/exception.py
swot_simulator/l2a-highres.xml
swot_simulator/l2b-expert.xml
swot_simulator/l2b-ssh.xml
swot_simulator/l2b-windwave.xml
swot_simulator/launcher.py
swot_simulator/logbook.py
swot_simulator/math.py
swot_simulator/nadir-gpr.xml
swot_simulator/netcdf.py
swot_simulator/orbit_propagator.py
swot_simulator/product_specification.py
swot_simulator/random_signal.py
swot_simulator/settings.py
swot_simulator/version.py
swot_simulator.egg-info/PKG-INFO
swot_simulator.egg-info/SOURCES.txt
swot_simulator.egg-info/dependency_links.txt
swot_simulator.egg-info/entry_points.txt
swot_simulator.egg-info/requires.txt
swot_simulator.egg-info/top_level.txt
swot_simulator/data/dt_global_allsat_phy_l4_20181231_20190515.nc
swot_simulator/data/dt_global_allsat_phy_l4_20190101_20190515.nc
swot_simulator/data/dt_global_allsat_phy_l4_20190102_20190515.nc
swot_simulator/data/dt_global_allsat_phy_l4_20190103_20190515.nc
swot_simulator/data/ephemeris_calval_june2015_ell.txt
swot_simulator/data/ephemeris_science_sept2015_ell.txt
swot_simulator/data/error_spectrum.nc
swot_simulator/data/karin_noise_v2.nc
swot_simulator/data/l2_lr_expert.py
swot_simulator/data/l2_lr_unsmoothed.py
swot_simulator/error/__init__.py
swot_simulator/error/altimeter.py
swot_simulator/error/baseline_dilation.py
swot_simulator/error/corrected_roll_phase.py
swot_simulator/error/generator.py
swot_simulator/error/karin.py
swot_simulator/error/orbital.py
swot_simulator/error/roll_phase.py
swot_simulator/error/timing.py
swot_simulator/error/wet_troposphere.py
swot_simulator/plugins/__init__.py
swot_simulator/plugins/data_handler.py
swot_simulator/plugins/ssh/__init__.py
swot_simulator/plugins/ssh/aviso.py
swot_simulator/plugins/ssh/hycom.py
swot_simulator/plugins/ssh/mitgcm.py
swot_simulator/plugins/ssh/mitgcm_ww3.py
swot_simulator/plugins/ssh/nemo.py
swot_simulator/plugins/ssh/symphonie.py
swot_simulator/plugins/swh/__init__.py
swot_simulator/plugins/swh/ww3.py
tests/__init__.py
tests/test_error_generation.py
tests/test_launcher.py
tests/test_random_signal.py