Metadata-Version: 2.1
Name: swot-simulator
Version: 1.2.1
Summary: Simulate SWOT measurements on sea surface height with simulated errors
Home-page: https://github.com/CNES/swot_simulator
Author: CNES/JPL
Author-email: fbriol@gmail.com
License: UNKNOWN
Platform: UNKNOWN
Classifier: Programming Language :: Python :: 3
Classifier: License :: OSI Approved :: MIT License
Classifier: Operating System :: OS Independent
Requires-Python: >=3.6
